Workbook
Name NativeTimeline_Date: #N/A
Name Slicer_Ad: #N/A
Name Slicer_Campaign: #N/A
Name Slicer_Channel: #N/A
Name Slicer_City_Location: #N/A
Name Slicer_Device: #N/A
Name Table: '5b'!$B$4:$E$904

Sheet Classwork 1
A2: gender | B2: race/ethnicity | C2: parental level of education | D2: lunch | E2: test preparation course | F2: math score | G2: reading score | H2: writing score | I2: Total | J2: Minimum | K2: Maximum | L2: Average | M2: Rank
A3: female | B3: group B | C3: bachelor's degree | D3: standard | E3: none | F3: 72 | G3: 72 | H3: 74 | I3: =SUM(F3:H3) -> 218 | J3: =MIN(F3:H3) -> 72 | K3: =MAX(F3:H3) -> 74 | L3: =AVERAGE(F3:H3) -> 72.666667 | M3: =RANK(L3,$L$3:$L$1002,0) -> 379
A4: female | B4: group C | C4: some college | D4: standard | E4: completed | F4: 69 | G4: 90 | H4: 88 | I4: =SUM(F4:H4) -> 247 | J4: =MIN(F4:H4) -> 69 | K4: =MAX(F4:H4) -> 90 | L4: =AVERAGE(F4:H4) -> 82.333333 | M4: =RANK(L4,$L$3:$L$1002,0) -> 155
A5: female | B5: group B | C5: master's degree | D5: standard | E5: none | F5: 90 | G5: 95 | H5: 93 | I5: =SUM(F5:H5) -> 278 | J5: =MIN(F5:H5) -> 90 | K5: =MAX(F5:H5) -> 95 | L5: =AVERAGE(F5:H5) -> 92.666667 | M5: =RANK(L5,$L$3:$L$1002,0) -> 31
A6: male | B6: group A | C6: associate's degree | D6: free/reduced | E6: none | F6: 47 | G6: 57 | H6: 44 | I6: =SUM(F6:H6) -> 148 | J6: =MIN(F6:H6) -> 44 | K6: =MAX(F6:H6) -> 57 | L6: =AVERAGE(F6:H6) -> 49.333333 | M6: =RANK(L6,$L$3:$L$1002,0) -> 901
A7: male | B7: group C | C7: some college | D7: standard | E7: none | F7: 76 | G7: 78 | H7: 75 | I7: =SUM(F7:H7) -> 229 | J7: =MIN(F7:H7) -> 75 | K7: =MAX(F7:H7) -> 78 | L7: =AVERAGE(F7:H7) -> 76.333333 | M7: =RANK(L7,$L$3:$L$1002,0) -> 282
A8: female | B8: group B | C8: associate's degree | D8: standard | E8: none | F8: 71 | G8: 83 | H8: 78 | I8: =SUM(F8:H8) -> 232 | J8: =MIN(F8:H8) -> 71 | K8: =MAX(F8:H8) -> 83 | L8: =AVERAGE(F8:H8) -> 77.333333 | M8: =RANK(L8,$L$3:$L$1002,0) -> 255
A9: female | B9: group B | C9: some college | D9: standard | E9: completed | F9: 88 | G9: 95 | H9: 92 | I9: =SUM(F9:H9) -> 275 | J9: =MIN(F9:H9) -> 88 | K9: =MAX(F9:H9) -> 95 | L9: =AVERAGE(F9:H9) -> 91.666667 | M9: =RANK(L9,$L$3:$L$1002,0) -> 37
A10: male | B10: group B | C10: some college | D10: free/reduced | E10: none | F10: 40 | G10: 43 | H10: 39 | I10: =SUM(F10:H10) -> 122 | J10: =MIN(F10:H10) -> 39 | K10: =MAX(F10:H10) -> 43 | L10: =AVERAGE(F10:H10) -> 40.666667 | M10: =RANK(L10,$L$3:$L$1002,0) -> 967
A11: male | B11: group D | C11: high school | D11: free/reduced | E11: completed | F11: 64 | G11: 64 | H11: 67 | I11: =SUM(F11:H11) -> 195 | J11: =MIN(F11:H11) -> 64 | K11: =MAX(F11:H11) -> 67 | L11: =AVERAGE(F11:H11) -> 65 | M11: =RANK(L11,$L$3:$L$1002,0) -> 593
A12: female | B12: group B | C12: high school | D12: free/reduced | E12: none | F12: 38 | G12: 60 | H12: 50 | I12: =SUM(F12:H12) -> 148 | J12: =MIN(F12:H12) -> 38 | K12: =MAX(F12:H12) -> 60 | L12: =AVERAGE(F12:H12) -> 49.333333 | M12: =RANK(L12,$L$3:$L$1002,0) -> 901
A13: male | B13: group C | C13: associate's degree | D13: standard | E13: none | F13: 58 | G13: 54 | H13: 52 | I13: =SUM(F13:H13) -> 164 | J13: =MIN(F13:H13) -> 52 | K13: =MAX(F13:H13) -> 58 | L13: =AVERAGE(F13:H13) -> 54.666667 | M13: =RANK(L13,$L$3:$L$1002,0) -> 810
A14: male | B14: group D | C14: associate's degree | D14: standard | E14: none | F14: 40 | G14: 52 | H14: 43 | I14: =SUM(F14:H14) -> 135 | J14: =MIN(F14:H14) -> 40 | K14: =MAX(F14:H14) -> 52 | L14: =AVERAGE(F14:H14) -> 45 | M14: =RANK(L14,$L$3:$L$1002,0) -> 945
... A1002: female | B1002: group D | C1002: some college | D1002: free/reduced | E1002: none | F1002: 77 | G1002: 86 | H1002: 86 | I1002: =SUM(F1002:H1002) -> 249 | J1002: =MIN(F1002:H1002) -> 77 | K1002: =MAX(F1002:H1002) -> 86 | L1002: =AVERAGE(F1002:H1002) -> 83 | M1002: =RANK(L1002,$L$3:$L$1002,0) -> 140

Sheet Classwork 2
B3: gender | C3: race/ethnicity | D3: Enrollment_num | E3: Country | F3: City | G3: State | H3: Region | I3: Country Corrected | J3: Address | K3: Address Short | L3: Unique Identifier | M3: Enrollment Year
B4: female | C4: group B | D4: CA-2016-152156 | E4: United States | F4: Henderson | G4: Kentucky | H4: South | I4: =TRIM(E4) -> United States | J4: =CONCATENATE("'",F4,","," ",G4," ","(",I4,")","'") -> 'Henderson, Kentucky (United States)' | K4: =SUBSTITUTE(J4,"United States","US",1) -> 'Henderson, Kentucky (US)' | L4: =RIGHT(D4,6) -> 152156 | M4: =MID(D4,4,4) -> 2016
B5: female | C5: group C | D5: CA-2016-138688 | E5: United States | F5: Henderson | G5: Kentucky | H5: South | I5: =TRIM(E5) -> United States | J5: =CONCATENATE("'",F5,","," ",G5," ","(",I5,")","'") -> 'Henderson, Kentucky (United States)' | K5: =SUBSTITUTE(J5,"United States","US",1) -> 'Henderson, Kentucky (US)' | L5: =RIGHT(D5,6) -> 138688 | M5: =MID(D5,4,4) -> 2016
B6: female | C6: group B | D6: US-2015-108966 | E6: United States | F6: Los Angeles | G6: California | H6: West | I6: =TRIM(E6) -> United States | J6: =CONCATENATE("'",F6,","," ",G6," ","(",I6,")","'") -> 'Los Angeles, California (United States)' | K6: =SUBSTITUTE(J6,"United States","US",1) -> 'Los Angeles, California (US)' | L6: =RIGHT(D6,6) -> 108966 | M6: =MID(D6,4,4) -> 2015
B7: male | C7: group A | D7: CA-2014-115812 | E7: United States | F7: Fort Lauderdale | G7: Florida | H7: South | I7: =TRIM(E7) -> United States | J7: =CONCATENATE("'",F7,","," ",G7," ","(",I7,")","'") -> 'Fort Lauderdale, Florida (United States)' | K7: =SUBSTITUTE(J7,"United States","US",1) -> 'Fort Lauderdale, Florida (US)' | L7: =RIGHT(D7,6) -> 115812 | M7: =MID(D7,4,4) -> 2014
B8: male | C8: group C | D8: CA-2017-114412 | E8: United States | F8: Fort Lauderdale | G8: Florida | H8: South | I8: =TRIM(E8) -> United States | J8: =CONCATENATE("'",F8,","," ",G8," ","(",I8,")","'") -> 'Fort Lauderdale, Florida (United States)' | K8: =SUBSTITUTE(J8,"United States","US",1) -> 'Fort Lauderdale, Florida (US)' | L8: =RIGHT(D8,6) -> 114412 | M8: =MID(D8,4,4) -> 2017
B9: female | C9: group B | D9: CA-2016-161389 | E9: United States | F9: Los Angeles | G9: California | H9: West | I9: =TRIM(E9) -> United States | J9: =CONCATENATE("'",F9,","," ",G9," ","(",I9,")","'") -> 'Los Angeles, California (United States)' | K9: =SUBSTITUTE(J9,"United States","US",1) -> 'Los Angeles, California (US)' | L9: =RIGHT(D9,6) -> 161389 | M9: =MID(D9,4,4) -> 2016
B10: female | C10: group B | D10: US-2015-118983 | E10: United States | F10: Los Angeles | G10: California | H10: West | I10: =TRIM(E10) -> United States | J10: =CONCATENATE("'",F10,","," ",G10," ","(",I10,")","'") -> 'Los Angeles, California (United States)' | K10: =SUBSTITUTE(J10,"United States","US",1) -> 'Los Angeles, California (US)' | L10: =RIGHT(D10,6) -> 118983 | M10: =MID(D10,4,4) -> 2015
B11: male | C11: group B | D11: CA-2014-105893 | E11: United States | F11: Los Angeles | G11: California | H11: West | I11: =TRIM(E11) -> United States | J11: =CONCATENATE("'",F11,","," ",G11," ","(",I11,")","'") -> 'Los Angeles, California (United States)' | K11: =SUBSTITUTE(J11,"United States","US",1) -> 'Los Angeles, California (US)' | L11: =RIGHT(D11,6) -> 105893 | M11: =MID(D11,4,4) -> 2014
B12: male | C12: group D | D12: CA-2014-167164 | E12: United States | F12: Los Angeles | G12: California | H12: West | I12: =TRIM(E12) -> United States | J12: =CONCATENATE("'",F12,","," ",G12," ","(",I12,")","'") -> 'Los Angeles, California (United States)' | K12: =SUBSTITUTE(J12,"United States","US",1) -> 'Los Angeles, California (US)' | L12: =RIGHT(D12,6) -> 167164 | M12: =MID(D12,4,4) -> 2014
B13: female | C13: group B | D13: CA-2014-143336 | E13: United States | F13: Los Angeles | G13: California | H13: West | I13: =TRIM(E13) -> United States | J13: =CONCATENATE("'",F13,","," ",G13," ","(",I13,")","'") -> 'Los Angeles, California (United States)' | K13: =SUBSTITUTE(J13,"United States","US",1) -> 'Los Angeles, California (US)' | L13: =RIGHT(D13,6) -> 143336 | M13: =MID(D13,4,4) -> 2014
B14: male | C14: group C | D14: CA-2016-137330 | E14: United States | F14: Los Angeles | G14: California | H14: West | I14: =TRIM(E14) -> United States | J14: =CONCATENATE("'",F14,","," ",G14," ","(",I14,")","'") -> 'Los Angeles, California (United States)' | K14: =SUBSTITUTE(J14,"United States","US",1) -> 'Los Angeles, California (US)' | L14: =RIGHT(D14,6) -> 137330 | M14: =MID(D14,4,4) -> 2016
B15: male | C15: group D | D15: US-2017-156909 | E15: United States | F15: Los Angeles | G15: California | H15: West | I15: =TRIM(E15) -> United States | J15: =CONCATENATE("'",F15,","," ",G15," ","(",I15,")","'") -> 'Los Angeles, California (United States)' | K15: =SUBSTITUTE(J15,"United States","US",1) -> 'Los Angeles, California (US)' | L15: =RIGHT(D15,6) -> 156909 | M15: =MID(D15,4,4) -> 2017
... B258: male | C258: group D | D258: CA-2014-103849 | E258: United States | F258: Chicago | G258: Illinois | H258: Central | I258: =TRIM(E258) -> United States | J258: =CONCATENATE("'",F258,","," ",G258," ","(",I258,")","'") -> 'Chicago, Illinois (United States)' | K258: =SUBSTITUTE(J258,"United States","US",1) -> 'Chicago, Illinois (US)' | L258: =RIGHT(D258,6) -> 103849 | M258: =MID(D258,4,4) -> 2014
B259: female | C259: group E | D259: CA-2017-162929 | E259: United States | F259: Chicago | G259: Illinois | H259: Central | I259: =TRIM(E259) -> United States | J259: =CONCATENATE(F259,","," ",G259," ","(",I259,")") -> Chicago, Illinois (United States) | K259: =SUBSTITUTE(J259,"United States","US",1) -> Chicago, Illinois (US) | L259: =RIGHT(D259,6) -> 162929 | M259: =MID(D259,4,4) -> 2017
B260: female | C260: group C | D260: CA-2015-113173 | E260: United States | F260: Chicago | G260: Illinois | H260: Central | I260: =TRIM(E260) -> United States | J260: =CONCATENATE(F260,","," ",G260," ","(",I260,")") -> Chicago, Illinois (United States) | K260: =SUBSTITUTE(J260,"United States","US",1) -> Chicago, Illinois (US) | L260: =RIGHT(D260,6) -> 113173 | M260: =MID(D260,4,4) -> 2015
B261: male | C261: group C | D261: CA-2016-136406 | E261: United States | F261: Chicago | G261: Illinois | H261: Central | I261: =TRIM(E261) -> United States | J261: =CONCATENATE(F261,","," ",G261," ","(",I261,")") -> Chicago, Illinois (United States) | K261: =SUBSTITUTE(J261,"United States","US",1) -> Chicago, Illinois (US) | L261: =RIGHT(D261,6) -> 136406 | M261: =MID(D261,4,4) -> 2016
B262: female | C262: group B | D262: CA-2017-112774 | E262: United States | F262: New York City | G262: New York | H262: East | I262: =TRIM(E262) -> United States | J262: =CONCATENATE(F262,","," ",G262," ","(",I262,")") -> New York City, New York (United States) | K262: =SUBSTITUTE(J262,"United States","US",1) -> New York City, New York (US) | L262: =RIGHT(D262,6) -> 112774 | M262: =MID(D262,4,4) -> 2017
B263: female | C263: group C | D263: CA-2017-101945 | E263: United States | F263: New York City | G263: New York | H263: East | I263: =TRIM(E263) -> United States | J263: =CONCATENATE(F263,","," ",G263," ","(",I263,")") -> New York City, New York (United States) | K263: =SUBSTITUTE(J263,"United States","US",1) -> New York City, New York (US) | L263: =RIGHT(D263,6) -> 101945 | M263: =MID(D263,4,4) -> 2017
B264: female | C264: group C | D264: CA-2017-100650 | E264: United States | F264: New York City | G264: New York | H264: East | I264: =TRIM(E264) -> United States | J264: =CONCATENATE(F264,","," ",G264," ","(",I264,")") -> New York City, New York (United States) | K264: =SUBSTITUTE(J264,"United States","US",1) -> New York City, New York (US) | L264: =RIGHT(D264,6) -> 100650 | M264: =MID(D264,4,4) -> 2017
B265: male | C265: group C | D265: CA-2014-155852 | E265: United States | F265: Pasadena | G265: Texas | H265: Central | I265: =TRIM(E265) -> United States | J265: =CONCATENATE(F265,","," ",G265," ","(",I265,")") -> Pasadena, Texas (United States) | K265: =SUBSTITUTE(J265,"United States","US",1) -> Pasadena, Texas (US) | L265: =RIGHT(D265,6) -> 155852 | M265: =MID(D265,4,4) -> 2014
B266: female | C266: group C | D266: CA-2016-113243 | E266: United States | F266: Houston | G266: Texas | H266: Central | I266: =TRIM(E266) -> United States | J266: =CONCATENATE(F266,","," ",G266," ","(",I266,")") -> Houston, Texas (United States) | K266: =SUBSTITUTE(J266,"United States","US",1) -> Houston, Texas (US) | L266: =RIGHT(D266,6) -> 113243 | M266: =MID(D266,4,4) -> 2016
B267: female | C267: group E | D267: CA-2017-118731 | E267: United States | F267: Houston | G267: Texas | H267: Central | I267: =TRIM(E267) -> United States | J267: =CONCATENATE(F267,","," ",G267," ","(",I267,")") -> Houston, Texas (United States) | K267: =SUBSTITUTE(J267,"United States","US",1) -> Houston, Texas (US) | L267: =RIGHT(D267,6) -> 118731 | M267: =MID(D267,4,4) -> 2017
B268: male | C268: group D | D268: CA-2014-145576 | E268: United States | F268: Chicago | G268: Illinois | H268: Central | I268: =TRIM(E268) -> United States | J268: =CONCATENATE(F268,","," ",G268," ","(",I268,")") -> Chicago, Illinois (United States) | K268: =SUBSTITUTE(J268,"United States","US",1) -> Chicago, Illinois (US) | L268: =RIGHT(D268,6) -> 145576 | M268: =MID(D268,4,4) -> 2014
B269: male | C269: group D | D269: CA-2015-130736 | E269: United States | F269: Brentwood | G269: California | H269: West | I269: =TRIM(E269) -> United States | J269: =CONCATENATE(F269,","," ",G269," ","(",I269,")") -> Brentwood, California (United States) | K269: =SUBSTITUTE(J269,"United States","US",1) -> Brentwood, California (US) | L269: =RIGHT(D269,6) -> 130736 | M269: =MID(D269,4,4) -> 2015
B270: female | C270: group C | D270: CA-2017-137099 | E270: United States | F270: Chapel Hill | G270: North Carolina | H270: South | I270: =TRIM(E270) -> United States | J270: =CONCATENATE(F270,","," ",G270," ","(",I270,")") -> Chapel Hill, North Carolina (United States) | K270: =SUBSTITUTE(J270,"United States","US",1) -> Chapel Hill, North Carolina (US) | L270: =RIGHT(D270,6) -> 137099 | M270: =MID(D270,4,4) -> 2017
... B1003: female | C1003: group D | D1003: CA-2015-142237 | E1003: United States | F1003: Henderson | G1003: Kentucky | H1003: South | I1003: =TRIM(E1003) -> United States | J1003: =CONCATENATE(F1003,","," ",G1003," ","(",I1003,")") -> Henderson, Kentucky (United States) | K1003: =SUBSTITUTE(J1003,"United States","US",1) -> Henderson, Kentucky (US) | L1003: =RIGHT(D1003,6) -> 142237 | M1003: =MID(D1003,4,4) -> 2015

Sheet Classwork 3
B3: gender | C3: race/ethnicity | D3: parental level of education | E3: lunch | F3: test preparation course | G3: math score | H3: reading score | I3: writing score | J3: Fail? | K3: Grade | L3: Status
B4: female | C4: group B | D4: bachelor's degree | E4: standard | F4: none | G4: 72 | H4: 72 | I4: 74 | J4: =IF(OR((G4<35),(H4<35),(I4<35)),"TRUE","FALSE") -> FALSE | K4: =IF(AND(G4>75,H4>75,I4>75),"A",IF(J4="TRUE","C","B")) -> B | L4: =IF(AND(F4="none",J4="TRUE"),"Repeat Course", "In Progress") -> In Progress | O4: Grades Count
B5: female | C5: group C | D5: some college | E5: standard | F5: completed | G5: 69 | H5: 90 | I5: 88 | J5: =IF(OR((G5<35),(H5<35),(I5<35)),"TRUE","FALSE") -> FALSE | K5: =IF(AND(G5>75,H5>75,I5>75),"A",IF(J5="TRUE","C","B")) -> B | L5: =IF(AND(F5="none",J5="TRUE"),"Repeat Course", "In Progress") -> In Progress | O5: ="A" -> A | P5: =COUNTIF($K$4:$K$1003,O5) -> 188
B6: female | C6: group B | D6: master's degree | E6: standard | F6: none | G6: 90 | H6: 95 | I6: 93 | J6: =IF(OR((G6<35),(H6<35),(I6<35)),"TRUE","FALSE") -> FALSE | K6: =IF(AND(G6>75,H6>75,I6>75),"A",IF(J6="TRUE","C","B")) -> A | L6: =IF(AND(F6="none",J6="TRUE"),"Repeat Course", "In Progress") -> In Progress | O6: ="B" -> B | P6: =COUNTIF($K$4:$K$1003,O6) -> 783
B7: male | C7: group A | D7: associate's degree | E7: free/reduced | F7: none | G7: 47 | H7: 57 | I7: 44 | J7: =IF(OR((G7<35),(H7<35),(I7<35)),"TRUE","FALSE") -> FALSE | K7: =IF(AND(G7>75,H7>75,I7>75),"A",IF(J7="TRUE","C","B")) -> B | L7: =IF(AND(F7="none",J7="TRUE"),"Repeat Course", "In Progress") -> In Progress | O7: ="C" -> C | P7: =COUNTIF($K$4:$K$1003,O7) -> 29
B8: male | C8: group C | D8: some college | E8: standard | F8: none | G8: 76 | H8: 78 | I8: 75 | J8: =IF(OR((G8<35),(H8<35),(I8<35)),"TRUE","FALSE") -> FALSE | K8: =IF(AND(G8>75,H8>75,I8>75),"A",IF(J8="TRUE","C","B")) -> B | L8: =IF(AND(F8="none",J8="TRUE"),"Repeat Course", "In Progress") -> In Progress
B9: female | C9: group B | D9: associate's degree | E9: standard | F9: none | G9: 71 | H9: 83 | I9: 78 | J9: =IF(OR((G9<35),(H9<35),(I9<35)),"TRUE","FALSE") -> FALSE | K9: =IF(AND(G9>75,H9>75,I9>75),"A",IF(J9="TRUE","C","B")) -> B | L9: =IF(AND(F9="none",J9="TRUE"),"Repeat Course", "In Progress") -> In Progress
B10: female | C10: group B | D10: some college | E10: standard | F10: completed | G10: 88 | H10: 95 | I10: 92 | J10: =IF(OR((G10<35),(H10<35),(I10<35)),"TRUE","FALSE") -> FALSE | K10: =IF(AND(G10>75,H10>75,I10>75),"A",IF(J10="TRUE","C","B")) -> A | L10: =IF(AND(F10="none",J10="TRUE"),"Repeat Course", "In Progress") -> In Progress
B11: male | C11: group B | D11: some college | E11: free/reduced | F11: none | G11: 40 | H11: 43 | I11: 39 | J11: =IF(OR((G11<35),(H11<35),(I11<35)),"TRUE","FALSE") -> FALSE | K11: =IF(AND(G11>75,H11>75,I11>75),"A",IF(J11="TRUE","C","B")) -> B | L11: =IF(AND(F11="none",J11="TRUE"),"Repeat Course", "In Progress") -> In Progress
B12: male | C12: group D | D12: high school | E12: free/reduced | F12: completed | G12: 64 | H12: 64 | I12: 67 | J12: =IF(OR((G12<35),(H12<35),(I12<35)),"TRUE","FALSE") -> FALSE | K12: =IF(AND(G12>75,H12>75,I12>75),"A",IF(J12="TRUE","C","B")) -> B | L12: =IF(AND(F12="none",J12="TRUE"),"Repeat Course", "In Progress") -> In Progress
B13: female | C13: group B | D13: high school | E13: free/reduced | F13: none | G13: 38 | H13: 60 | I13: 50 | J13: =IF(OR((G13<35),(H13<35),(I13<35)),"TRUE","FALSE") -> FALSE | K13: =IF(AND(G13>75,H13>75,I13>75),"A",IF(J13="TRUE","C","B")) -> B | L13: =IF(AND(F13="none",J13="TRUE"),"Repeat Course", "In Progress") -> In Progress
B14: male | C14: group C | D14: associate's degree | E14: standard | F14: none | G14: 58 | H14: 54 | I14: 52 | J14: =IF(OR((G14<35),(H14<35),(I14<35)),"TRUE","FALSE") -> FALSE | K14: =IF(AND(G14>75,H14>75,I14>75),"A",IF(J14="TRUE","C","B")) -> B | L14: =IF(AND(F14="none",J14="TRUE"),"Repeat Course", "In Progress") -> In Progress
B15: male | C15: group D | D15: associate's degree | E15: standard | F15: none | G15: 40 | H15: 52 | I15: 43 | J15: =IF(OR((G15<35),(H15<35),(I15<35)),"TRUE","FALSE") -> FALSE | K15: =IF(AND(G15>75,H15>75,I15>75),"A",IF(J15="TRUE","C","B")) -> B | L15: =IF(AND(F15="none",J15="TRUE"),"Repeat Course", "In Progress") -> In Progress
B16: female | C16: group B | D16: high school | E16: standard | F16: none | G16: 65 | H16: 81 | I16: 73 | J16: =IF(OR((G16<35),(H16<35),(I16<35)),"TRUE","FALSE") -> FALSE | K16: =IF(AND(G16>75,H16>75,I16>75),"A",IF(J16="TRUE","C","B")) -> B | L16: =IF(AND(F16="none",J16="TRUE"),"Repeat Course", "In Progress") -> In Progress
B17: male | C17: group A | D17: some college | E17: standard | F17: completed | G17: 78 | H17: 72 | I17: 70 | J17: =IF(OR((G17<35),(H17<35),(I17<35)),"TRUE","FALSE") -> FALSE | K17: =IF(AND(G17>75,H17>75,I17>75),"A",IF(J17="TRUE","C","B")) -> B | L17: =IF(AND(F17="none",J17="TRUE"),"Repeat Course", "In Progress") -> In Progress
B18: female | C18: group A | D18: master's degree | E18: standard | F18: none | G18: 50 | H18: 53 | I18: 58 | J18: =IF(OR((G18<35),(H18<35),(I18<35)),"TRUE","FALSE") -> FALSE | K18: =IF(AND(G18>75,H18>75,I18>75),"A",IF(J18="TRUE","C","B")) -> B | L18: =IF(AND(F18="none",J18="TRUE"),"Repeat Course", "In Progress") -> In Progress
B19: female | C19: group C | D19: some high school | E19: standard | F19: none | G19: 69 | H19: 75 | I19: 78 | J19: =IF(OR((G19<35),(H19<35),(I19<35)),"TRUE","FALSE") -> FALSE | K19: =IF(AND(G19>75,H19>75,I19>75),"A",IF(J19="TRUE","C","B")) -> B | L19: =IF(AND(F19="none",J19="TRUE"),"Repeat Course", "In Progress") -> In Progress
... B1003: female | C1003: group D | D1003: some college | E1003: free/reduced | F1003: none | G1003: 77 | H1003: 86 | I1003: 86 | J1003: =IF(OR((G1003<35),(H1003<35),(I1003<35)),"TRUE","FALSE") -> FALSE | K1003: =IF(AND(G1003>75,H1003>75,I1003>75),"A",IF(J1003="TRUE","C","B")) -> A | L1003: =IF(AND(F1003="none",J1003="TRUE"),"Repeat Course", "In Progress") -> In Progress

Sheet Classwork 4
D1: 45998 | I1: =MID(D1,4,2) -> 98
B3: Row ID | C3: Order ID | D3: Order Date | E3: Ship Date | F3: Customer ID | G3: Product ID | H3: Sales | I3: Order Month | J3: Ship Time in Days | L3: Order Count | O3: Average Processing time
B4: 1 | C4: CA-2016-152156 | D4: 42682 | E4: 42685 | F4: CG-12520 | G4: FUR-BO-10001798 | H4: 261.96 | I4: =MONTH(D4) -> 11 | J4: =ABS(SUM(D4-E4)) -> 3 | L4: Month | M4: Count | O4: In Days | P4: =AVERAGE(J4:J503) -> 4.088
B5: 2 | C5: CA-2016-152156 | D5: 42682 | E5: 42685 | F5: CG-12520 | G5: FUR-CH-10000454 | H5: 731.94 | I5: =MONTH(D5) -> 11 | J5: =ABS(SUM(D5-E5)) -> 3 | L5: 1 | M5: =COUNTIF($I$4:$I$503,L5) -> 13
B6: 3 | C6: CA-2016-138688 | D6: 42533 | E6: 42537 | F6: DV-13045 | G6: OFF-LA-10000240 | H6: 14.62 | I6: =MONTH(D6) -> 6 | J6: =ABS(SUM(D6-E6)) -> 4 | L6: 2 | M6: =COUNTIF($I$4:$I$503,L6) -> 7
B7: 4 | C7: US-2015-108966 | D7: 42288 | E7: 42295 | F7: SO-20335 | G7: FUR-TA-10000577 | H7: 957.5775 | I7: =MONTH(D7) -> 10 | J7: =ABS(SUM(D7-E7)) -> 7 | L7: 3 | M7: =COUNTIF($I$4:$I$503,L7) -> 15
B8: 5 | C8: US-2015-108966 | D8: 42288 | E8: 42295 | F8: SO-20335 | G8: OFF-ST-10000760 | H8: 22.368 | I8: =MONTH(D8) -> 10 | J8: =ABS(SUM(D8-E8)) -> 7 | L8: 4 | M8: =COUNTIF($I$4:$I$503,L8) -> 52
B9: 6 | C9: CA-2014-115812 | D9: 41799 | E9: 41804 | F9: BH-11710 | G9: FUR-FU-10001487 | H9: 48.86 | I9: =MONTH(D9) -> 6 | J9: =ABS(SUM(D9-E9)) -> 5 | L9: 5 | M9: =COUNTIF($I$4:$I$503,L9) -> 11
B10: 7 | C10: CA-2014-115812 | D10: 41799 | E10: 41804 | F10: BH-11710 | G10: OFF-AR-10002833 | H10: 7.28 | I10: =MONTH(D10) -> 6 | J10: =ABS(SUM(D10-E10)) -> 5 | L10: 6 | M10: =COUNTIF($I$4:$I$503,L10) -> 63
B11: 8 | C11: CA-2014-115812 | D11: 41799 | E11: 41804 | F11: BH-11710 | G11: TEC-PH-10002275 | H11: 907.152 | I11: =MONTH(D11) -> 6 | J11: =ABS(SUM(D11-E11)) -> 5 | L11: 7 | M11: =COUNTIF($I$4:$I$503,L11) -> 25
B12: 9 | C12: CA-2014-115812 | D12: 41799 | E12: 41804 | F12: BH-11710 | G12: OFF-BI-10003910 | H12: 18.504 | I12: =MONTH(D12) -> 6 | J12: =ABS(SUM(D12-E12)) -> 5 | L12: 8 | M12: =COUNTIF($I$4:$I$503,L12) -> 28
B13: 10 | C13: CA-2014-115812 | D13: 41799 | E13: 41804 | F13: BH-11710 | G13: OFF-AP-10002892 | H13: 114.9 | I13: =MONTH(D13) -> 6 | J13: =ABS(SUM(D13-E13)) -> 5 | L13: 9 | M13: =COUNTIF($I$4:$I$503,L13) -> 82
B14: 11 | C14: CA-2014-115812 | D14: 41799 | E14: 41804 | F14: BH-11710 | G14: FUR-TA-10001539 | H14: 1706.184 | I14: =MONTH(D14) -> 6 | J14: =ABS(SUM(D14-E14)) -> 5 | L14: 10 | M14: =COUNTIF($I$4:$I$503,L14) -> 51
B15: 12 | C15: CA-2014-115812 | D15: 41799 | E15: 41804 | F15: BH-11710 | G15: TEC-PH-10002033 | H15: 911.424 | I15: =MONTH(D15) -> 6 | J15: =ABS(SUM(D15-E15)) -> 5 | L15: 11 | M15: =COUNTIF($I$4:$I$503,L15) -> 68
B16: 13 | C16: CA-2017-114412 | D16: 42840 | E16: 42845 | F16: AA-10480 | G16: OFF-PA-10002365 | H16: 15.552 | I16: =MONTH(D16) -> 4 | J16: =ABS(SUM(D16-E16)) -> 5 | L16: 12 | M16: =COUNTIF($I$4:$I$503,L16) -> 85
B17: 14 | C17: CA-2016-161389 | D17: 42709 | E17: 42714 | F17: IM-15070 | G17: OFF-BI-10003656 | H17: 407.976 | I17: =MONTH(D17) -> 12 | J17: =ABS(SUM(D17-E17)) -> 5
B18: 15 | C18: US-2015-118983 | D18: 42330 | E18: 42334 | F18: HP-14815 | G18: OFF-AP-10002311 | H18: 68.81 | I18: =MONTH(D18) -> 11 | J18: =ABS(SUM(D18-E18)) -> 4
B19: 16 | C19: US-2015-118983 | D19: 42330 | E19: 42334 | F19: HP-14815 | G19: OFF-BI-10000756 | H19: 2.544 | I19: =MONTH(D19) -> 11 | J19: =ABS(SUM(D19-E19)) -> 4
B20: 17 | C20: CA-2014-105893 | D20: 41954 | E20: 41961 | F20: PK-19075 | G20: OFF-ST-10004186 | H20: 665.88 | I20: =MONTH(D20) -> 11 | J20: =ABS(SUM(D20-E20)) -> 7
B21: 18 | C21: CA-2014-167164 | D21: 41772 | E21: 41774 | F21: AG-10270 | G21: OFF-ST-10000107 | H21: 55.5 | I21: =MONTH(D21) -> 5 | J21: =ABS(SUM(D21-E21)) -> 2
B22: 19 | C22: CA-2014-143336 | D22: 41878 | E22: 41883 | F22: ZD-21925 | G22: OFF-AR-10003056 | H22: 8.56 | I22: =MONTH(D22) -> 8 | J22: =ABS(SUM(D22-E22)) -> 5
B23: 20 | C23: CA-2014-143336 | D23: 41878 | E23: 41883 | F23: ZD-21925 | G23: TEC-PH-10001949 | H23: 213.48 | I23: =MONTH(D23) -> 8 | J23: =ABS(SUM(D23-E23)) -> 5
B24: 21 | C24: CA-2014-143336 | D24: 41878 | E24: 41883 | F24: ZD-21925 | G24: OFF-BI-10002215 | H24: 22.72 | I24: =MONTH(D24) -> 8 | J24: =ABS(SUM(D24-E24)) -> 5
B25: 22 | C25: CA-2016-137330 | D25: 42713 | E25: 42717 | F25: KB-16585 | G25: OFF-AR-10000246 | H25: 19.46 | I25: =MONTH(D25) -> 12 | J25: =ABS(SUM(D25-E25)) -> 4
B26: 23 | C26: CA-2016-137330 | D26: 42713 | E26: 42717 | F26: KB-16585 | G26: OFF-AP-10001492 | H26: 60.34 | I26: =MONTH(D26) -> 12 | J26: =ABS(SUM(D26-E26)) -> 4
B27: 24 | C27: US-2017-156909 | D27: 42932 | E27: 42934 | F27: SF-20065 | G27: FUR-CH-10002774 | H27: 71.372 | I27: =MONTH(D27) -> 7 | J27: =ABS(SUM(D27-E27)) -> 2
B28: 25 | C28: CA-2015-106320 | D28: 42272 | E28: 42277 | F28: EB-13870 | G28: FUR-TA-10000577 | H28: 1044.63 | I28: =MONTH(D28) -> 9 | J28: =ABS(SUM(D28-E28)) -> 5
... B502: 499 | C502: CA-2016-126158 | D502: 42576 | E502: 42582 | F502: SC-20095 | G502: FUR-CH-10002602 | H502: 241.568 | I502: =MONTH(D502) -> 7 | J502: =ABS(SUM(D502-E502)) -> 6
B503: 500 | C503: CA-2016-126158 | D503: 42576 | E503: 42582 | F503: SC-20095 | I503: =MONTH(D503) -> 7 | J503: =ABS(SUM(D503-E503)) -> 6

Sheet Classwork 5
B3: User_ID | C3: Product_ID | D3: Gender | E3: Age | F3: Occupation | G3: Product_Category_1 | H3: Purchase | J3: Registeration rank of user with User_ID 1000652 | K3: =MATCH('5b'!B585,'5b'!B4:B904,0) -> 582
B4: 1000001 | C4: P00069042 | D4: =VLOOKUP(B4,'5b'!$B$4:$E$904,2,FALSE) -> F | E4: =INDEX(Table,MATCH('Classwork 5'!B4,'5b'!$B$4:$B$904,0),3) -> 0-17 | F4: =INDEX(Table,MATCH('Classwork 5'!B4,'5b'!$B$4:$B$904,0),4) -> 10 | G4: 3 | H4: 8370
B5: 1000001 | C5: P00248942 | D5: =VLOOKUP(B5,'5b'!$B$4:$E$904,2,FALSE) -> F | E5: =INDEX(Table,MATCH('Classwork 5'!B5,'5b'!$B$4:$B$904,0),3) -> 0-17 | F5: =INDEX(Table,MATCH('Classwork 5'!B5,'5b'!$B$4:$B$904,0),4) -> 10 | G5: 1 | H5: 15200
B6: 1000001 | C6: P00087842 | D6: =VLOOKUP(B6,'5b'!$B$4:$E$904,2,FALSE) -> F | E6: =INDEX(Table,MATCH('Classwork 5'!B6,'5b'!$B$4:$B$904,0),3) -> 0-17 | F6: =INDEX(Table,MATCH('Classwork 5'!B6,'5b'!$B$4:$B$904,0),4) -> 10 | G6: 12 | H6: 1422 | J6: 10th Customer's Occupation | K6: =INDEX('5b'!B4:E904,10,4) -> 1
B7: 1000001 | C7: P00085442 | D7: =VLOOKUP(B7,'5b'!$B$4:$E$904,2,FALSE) -> F | E7: =INDEX(Table,MATCH('Classwork 5'!B7,'5b'!$B$4:$B$904,0),3) -> 0-17 | F7: =INDEX(Table,MATCH('Classwork 5'!B7,'5b'!$B$4:$B$904,0),4) -> 10 | G7: 12 | H7: 1057
B8: 1000002 | C8: P00285442 | D8: =VLOOKUP(B8,'5b'!$B$4:$E$904,2,FALSE) -> M | E8: =INDEX(Table,MATCH('Classwork 5'!B8,'5b'!$B$4:$B$904,0),3) -> 55+ | F8: =INDEX(Table,MATCH('Classwork 5'!B8,'5b'!$B$4:$B$904,0),4) -> 16 | G8: 8 | H8: 7969
B9: 1000003 | C9: P00193542 | D9: =VLOOKUP(B9,'5b'!$B$4:$E$904,2,FALSE) -> M | E9: =INDEX(Table,MATCH('Classwork 5'!B9,'5b'!$B$4:$B$904,0),3) -> 26-35 | F9: =INDEX(Table,MATCH('Classwork 5'!B9,'5b'!$B$4:$B$904,0),4) -> 15 | G9: 1 | H9: 15227
B10: 1000004 | C10: P00184942 | D10: =VLOOKUP(B10,'5b'!$B$4:$E$904,2,FALSE) -> M | E10: =INDEX(Table,MATCH('Classwork 5'!B10,'5b'!$B$4:$B$904,0),3) -> 46-50 | F10: =INDEX(Table,MATCH('Classwork 5'!B10,'5b'!$B$4:$B$904,0),4) -> 7 | G10: 1 | H10: 19215
B11: 1000004 | C11: P00346142 | D11: =VLOOKUP(B11,'5b'!$B$4:$E$904,2,FALSE) -> M | E11: =INDEX(Table,MATCH('Classwork 5'!B11,'5b'!$B$4:$B$904,0),3) -> 46-50 | F11: =INDEX(Table,MATCH('Classwork 5'!B11,'5b'!$B$4:$B$904,0),4) -> 7 | G11: 1 | H11: 15854
B12: 1000004 | C12: P0097242 | D12: =VLOOKUP(B12,'5b'!$B$4:$E$904,2,FALSE) -> M | E12: =INDEX(Table,MATCH('Classwork 5'!B12,'5b'!$B$4:$B$904,0),3) -> 46-50 | F12: =INDEX(Table,MATCH('Classwork 5'!B12,'5b'!$B$4:$B$904,0),4) -> 7 | G12: 1 | H12: 15686
B13: 1000005 | C13: P00274942 | D13: =VLOOKUP(B13,'5b'!$B$4:$E$904,2,FALSE) -> M | E13: =INDEX(Table,MATCH('Classwork 5'!B13,'5b'!$B$4:$B$904,0),3) -> 26-35 | F13: =INDEX(Table,MATCH('Classwork 5'!B13,'5b'!$B$4:$B$904,0),4) -> 20 | G13: 8 | H13: 7871
B14: 1000005 | C14: P00251242 | D14: =VLOOKUP(B14,'5b'!$B$4:$E$904,2,FALSE) -> M | E14: =INDEX(Table,MATCH('Classwork 5'!B14,'5b'!$B$4:$B$904,0),3) -> 26-35 | F14: =INDEX(Table,MATCH('Classwork 5'!B14,'5b'!$B$4:$B$904,0),4) -> 20 | G14: 5 | H14: 5254
B15: 1000005 | C15: P00014542 | D15: =VLOOKUP(B15,'5b'!$B$4:$E$904,2,FALSE) -> M | E15: =INDEX(Table,MATCH('Classwork 5'!B15,'5b'!$B$4:$B$904,0),3) -> 26-35 | F15: =INDEX(Table,MATCH('Classwork 5'!B15,'5b'!$B$4:$B$904,0),4) -> 20 | G15: 8 | H15: 3957
B16: 1000005 | C16: P00031342 | D16: =VLOOKUP(B16,'5b'!$B$4:$E$904,2,FALSE) -> M | E16: =INDEX(Table,MATCH('Classwork 5'!B16,'5b'!$B$4:$B$904,0),3) -> 26-35 | F16: =INDEX(Table,MATCH('Classwork 5'!B16,'5b'!$B$4:$B$904,0),4) -> 20 | G16: 8 | H16: 6073
B17: 1000005 | C17: P00145042 | D17: =VLOOKUP(B17,'5b'!$B$4:$E$904,2,FALSE) -> M | E17: =INDEX(Table,MATCH('Classwork 5'!B17,'5b'!$B$4:$B$904,0),3) -> 26-35 | F17: =INDEX(Table,MATCH('Classwork 5'!B17,'5b'!$B$4:$B$904,0),4) -> 20 | G17: 1 | H17: 15665
B18: 1000006 | C18: P00231342 | D18: =VLOOKUP(B18,'5b'!$B$4:$E$904,2,FALSE) -> F | E18: =INDEX(Table,MATCH('Classwork 5'!B18,'5b'!$B$4:$B$904,0),3) -> 51-55 | F18: =INDEX(Table,MATCH('Classwork 5'!B18,'5b'!$B$4:$B$904,0),4) -> 9 | G18: 5 | H18: 5378
... B6276: 1001016 | C6276: P00220342 | D6276: =VLOOKUP(B6276,'5b'!$B$4:$E$904,2,FALSE) -> M | E6276: =INDEX(Table,MATCH('Classwork 5'!B6276,'5b'!$B$4:$B$904,0),3) -> 55+ | F6276: =INDEX(Table,MATCH('Classwork 5'!B6276,'5b'!$B$4:$B$904,0),4) -> 16 | G6276: 5 | H6276: 3596

Sheet 5b
B3: User_ID | C3: Gender | D3: Age | E3: Occupation
B4: 1000001 | C4: F | D4: 0-17 | E4: 10
B5: 1000002 | C5: M | D5: 55+ | E5: 16
B6: 1000003 | C6: M | D6: 26-35 | E6: 15
B7: 1000004 | C7: M | D7: 46-50 | E7: 7
B8: 1000005 | C8: M | D8: 26-35 | E8: 20
B9: 1000006 | C9: F | D9: 51-55 | E9: 9
B10: 1000007 | C10: M | D10: 36-45 | E10: 1
B11: 1000008 | C11: M | D11: 26-35 | E11: 12
B12: 1000009 | C12: M | D12: 26-35 | E12: 17
B13: 1000010 | C13: F | D13: 36-45 | E13: 1
B14: 1000011 | C14: F | D14: 26-35 | E14: 1
B15: 1000012 | C15: M | D15: 26-35 | E15: 12
... B904: 1001016 | C904: M | D904: 55+ | E904: 16

Sheet Classwork 6
A1: User_ID | B1: Gender | C1: Age | D1: Marital_Status
A2: 1000001 | B2: F | C2: 0-17 | D2: Unmarried
A3: 1000002 | B3: M | C3: 55+ | D3: Unmarried
A4: 1000003 | B4: M | C4: 26-35 | D4: Unmarried
A5: 1000004 | B5: M | C5: 46-50 | D5: Married
A6: 1000005 | B6: M | C6: 26-35 | D6: Married | F6: Age | G6: Marital_Status
A7: 1000006 | B7: F | C7: 51-55 | D7: Unmarried | F7: 18-25 | G7: Married
A8: 1000007 | B8: M | C8: 36-45 | D8: Married
A9: 1000008 | B9: M | C9: 26-35 | D9: Married | F9: User_ID | G9: Gender | H9: Age | I9: Marital_Status
A10: 1000009 | B10: M | C10: 26-35 | D10: Unmarried | F10: 1000047 | G10: M | H10: 18-25 | I10: Married
A11: 1000010 | B11: F | C11: 36-45 | D11: Married | F11: 1000049 | G11: M | H11: 18-25 | I11: Married
A12: 1000011 | B12: F | C12: 26-35 | D12: Unmarried | F12: 1000064 | G12: M | H12: 18-25 | I12: Married
A13: 1000012 | B13: M | C13: 26-35 | D13: Unmarried | F13: 1000135 | G13: M | H13: 18-25 | I13: Married
A14: 1000013 | B14: M | C14: 46-50 | D14: Married | F14: 1000138 | G14: M | H14: 18-25 | I14: Married
A15: 1000014 | B15: M | C15: 36-45 | D15: Unmarried | F15: 1000166 | G15: M | H15: 18-25 | I15: Married
A16: 1000015 | B16: M | C16: 26-35 | D16: Unmarried | F16: 1000191 | G16: M | H16: 18-25 | I16: Married
A17: 1000016 | B17: F | C17: 36-45 | D17: Married | F17: 1000203 | G17: F | H17: 18-25 | I17: Married
A18: 1000017 | B18: M | C18: 51-55 | D18: Unmarried | F18: 1000248 | G18: M | H18: 18-25 | I18: Married
A19: 1000018 | B19: F | C19: 18-25 | D19: Unmarried | F19: 1000273 | G19: M | H19: 18-25 | I19: Married
A20: 1000019 | B20: M | C20: 0-17 | D20: Unmarried | F20: 1000297 | G20: M | H20: 18-25 | I20: Married
A21: 1000020 | B21: M | C21: 26-35 | D21: Unmarried | F21: 1000305 | G21: F | H21: 18-25 | I21: Married
... A243: 1000248 | B243: M | C243: 18-25 | D243: Married | F243: 1006027 | G243: M | H243: 18-25 | I243: Married
A244: 1000249 | B244: F | C244: 18-25 | D244: Unmarried
A245: 1000250 | B245: M | C245: 36-45 | D245: Unmarried
A246: 1000251 | B246: M | C246: 55+ | D246: Married
A247: 1000252 | B247: M | C247: 26-35 | D247: Unmarried
A248: 1000253 | B248: F | C248: 26-35 | D248: Unmarried
A249: 1000254 | B249: M | C249: 36-45 | D249: Unmarried
A250: 1000255 | B250: M | C250: 36-45 | D250: Married
A251: 1000256 | B251: M | C251: 46-50 | D251: Unmarried
A252: 1000257 | B252: M | C252: 18-25 | D252: Unmarried
A253: 1000258 | B253: M | C253: 26-35 | D253: Married
A254: 1000259 | B254: M | C254: 26-35 | D254: Unmarried
A255: 1000260 | B255: M | C255: 18-25 | D255: Unmarried
... A5738: 1006040 | B5738: M | C5738: 26-35 | D5738: Unmarried

Sheet Financial Functions
A1: Assignment of finacial function
A4: 1. A has invested the US $100 in 2016. The payment has been made yearly. The interest rate is 10% p.a. What would be the FV in 2019?
A5: 2. Change every year. In 2017, 2018 & 2019, the interest rates would be 4%, 6% & 5% respectively. What would be the FV in 2019?
A6: 3 The future value of an investment in the US $100 in 2019. The payment has been made yearly. The interest rate is 10% p.a. What would be the PV as of now?
A7: 4. The US $1000 needs to be paid in full in 3 years. The interest rate is 10% p.a. and the payment needs to be done yearly. Find out the PMT.
A9: 1. FV | B9: =FV(E10,E11,E12,E13,0) -> 129.79 | D9: 1. FV | F9: 2. FV | H9: 3. PV | J9: 4. PMT
A10: 2. FV | B10: =FVSCHEDULE(G10,G12:G14) -> -115.752 | D10: Rate | E10: 0.1 | F10: Principal | G10: -100 | H10: Rate | I10: 0.1 | J10: Rate | K10: 0.1
A11: 3. PV | B11: =PV(I10,I11,I12,I13,0) -> 72.644628 | D11: Nper | E11: 3 | F11: Schedule | H11: Nper | I11: 3 | J11: Nper | K11: 3
A12: 4. PMT | B12: =PMT(K10,K11,K12) -> -402.1148 | D12: Pmt | E12: 1 | F12: 2017 | G12: 0.04 | H12: Pmt | I12: 1 | J12: Pv | K12: 1000
D13: Pv | E13: -100 | F13: 2018 | G13: 0.06 | H13: Fv | I13: -100 | J13: Fv
D14: Type | E14: 0 | F14: 2019 | G14: 0.05 | H14: Type | I14: 0 | J14: Type

Sheet Onyx Dataset Project
A1: Campaign | B1: Date | C1: City/Location | D1: Latitude | E1: Longitude | F1: Channel | G1: Device | H1: Ad | I1: Impressions | J1: CTR, % | K1: Clicks | L1: Daily Average CPC | M1: Spend, GBP | N1: Conversions | O1: Total conversion value, GBP | P1: Likes (Reactions) | Q1: Shares | R1: Comments
A2: Spring | B2: 44986 | C2: Birmingham | D2: 52.489471 | E2: -1.898575 | F2: Facebook | G2: Desktop | H2: Collection | I2: 1110.8 | J2: 0.0185 | K2: 20.5498 | L2: 1.3915 | M2: 28.595047 | N2: 1 | O2: 51.84 | P2: 45 | Q2: 4 | R2: 3
A3: Spring | B3: 44987 | C3: Birmingham | D3: 52.489471 | E3: -1.898575 | F3: Facebook | G3: Desktop | H3: Collection | I3: 1296.6 | J3: 0.011 | K3: 14.2626 | L3: 0.7245 | M3: 10.333254 | N3: 2 | O3: 40.32 | P3: 14 | Q3: 17 | R3: 10.5
A4: Spring | B4: 44988 | C4: Birmingham | D4: 52.489471 | E4: -1.898575 | F4: Facebook | G4: Desktop | H4: Collection | I4: 1264.4 | J4: 0.0132 | K4: 16.69008 | L4: 0.3795 | M4: 6.3338854 | N4: 4 | O4: 53.76 | P4: 24 | Q4: 1 | R4: 7.5
A5: Spring | B5: 44989 | C5: Birmingham | D5: 52.489471 | E5: -1.898575 | F5: Facebook | G5: Desktop | H5: Collection | I5: 837.8 | J5: 0.0159 | K5: 13.32102 | L5: 0.575 | M5: 7.6595865 | N5: 3 | O5: 25.92 | P5: 59 | Q5: 10 | R5: 6
A6: Spring | B6: 44990 | C6: Birmingham | D6: 52.489471 | E6: -1.898575 | F6: Facebook | G6: Desktop | H6: Collection | I6: 1599 | J6: 0.0144 | K6: 23.0256 | L6: 0.828 | M6: 19.065197 | N6: 2 | O6: 108.192 | P6: 44 | Q6: 17 | R6: 1.5
A7: Spring | B7: 44991 | C7: Birmingham | D7: 52.489471 | E7: -1.898575 | F7: Facebook | G7: Desktop | H7: Collection | I7: 893.6 | J7: 0.0192 | K7: 17.15712 | L7: 0.3105 | M7: 5.3272858 | N7: 4 | O7: 20.16 | P7: 57 | Q7: 3 | R7: 3
A8: Spring | B8: 44992 | C8: Birmingham | D8: 52.489471 | E8: -1.898575 | F8: Facebook | G8: Desktop | H8: Collection | I8: 1540.8 | J8: 0.0147 | K8: 22.64976 | L8: 1.5295 | M8: 34.642808 | N8: 0 | O8: 14.4 | P8: 44 | Q8: 0 | R8: 3
A9: Spring | B9: 44993 | C9: Birmingham | D9: 52.489471 | E9: -1.898575 | F9: Facebook | G9: Desktop | H9: Collection | I9: 994.8 | J9: 0.0144 | K9: 14.32512 | L9: 0.299 | M9: 4.2832109 | N9: 0 | O9: 23.04 | P9: 9 | Q9: 9 | R9: 6
A10: Spring | B10: 44994 | C10: Birmingham | D10: 52.489471 | E10: -1.898575 | F10: Facebook | G10: Desktop | H10: Collection | I10: 1336.6 | J10: 0.0122 | K10: 16.30652 | L10: 0.1725 | M10: 2.8128747 | N10: 2 | O10: 13.44 | P10: 33 | Q10: 12 | R10: 0
A11: Spring | B11: 44995 | C11: Birmingham | D11: 52.489471 | E11: -1.898575 | F11: Facebook | G11: Desktop | H11: Collection | I11: 1001.8 | J11: 0.0135 | K11: 13.5243 | L11: 0.529 | M11: 7.1543547 | N11: 4 | O11: 0 | P11: 9 | Q11: 17 | R11: 0
A12: Spring | B12: 44996 | C12: Birmingham | D12: 52.489471 | E12: -1.898575 | F12: Facebook | G12: Desktop | H12: Collection | I12: 1141.2 | J12: 0.0116 | K12: 13.23792 | L12: 0.8855 | M12: 11.722178 | N12: 4 | O12: 58.464 | P12: 37 | Q12: 4 | R12: 9
A13: Spring | B13: 44997 | C13: Birmingham | D13: 52.489471 | E13: -1.898575 | F13: Facebook | G13: Desktop | H13: Collection | I13: 1304.2 | J13: 0.0149 | K13: 19.43258 | L13: 1.1615 | M13: 22.570942 | N13: 4 | O13: 21.12 | P13: 29 | Q13: 6 | R13: 10.5
... A9901: Fall | B9901: 45260 | C9901: Manchester | D9901: 53.483959 | E9901: -2.244644 | F9901: Pinterest | G9901: Mobile | H9901: Discount | I9901: 1700 | J9901: 0.0057 | K9901: 9.1599 | L9901: 0.79 | M9901: 7.236321 | N9901: 7 | O9901: 298 | P9901: 69.6 | Q9901: 18 | R9901: 5
A9902: Total | I9902: =SUM(I2:I9901) -> 14645542 | J9902: =SUM(J2:J9901) -> 122.18594 | K9902: =SUM(K2:K9901) -> 181586.02 | L9902: =SUM(L2:L9901) -> 8949.337 | M9902: =SUM(M2:M9901) -> 163250.07 | N9902: =SUM(N2:N9901) -> 40252 | O9902: =SUM(O2:O9901) -> 1731700.4 | P9902: =SUM(P2:P9901) -> 608487.6 | ... R9902: =SUM(R2:R9901) -> 71530.5

Sheet Dictionary
A1: Campaign | B1: Marketing campaign
A2: Date | B2: Date for daily ad performance metrics
A3: City/Location | B3: Cities that were targeted by campaign
A4: Latitude | B4: Latitude for the cities
A5: Longitude | B5: Longitude for the cities
A6: Channel | B6: Channel where ads where displayed (Facebook, Instagram, Pinterest)
A7: Device | B7: Device from ads where viewed
A8: Ad | B8: Ads that where used within a campaign
A9: Impressions | B9: Daily impressions (times ad was shown to a viewer) for each ad
A10: CTR, % | B10: Daily average click-through rate for each ad
A11: Clicks | B11: Daily clicks for each ad
A12: Daily Average CPC | B12: Daily average cost-per-click for each ad
... A18: Comments | B18: Total daily comments per ad

Sheet PivotTable
A1: Date | B1: =TODAY() -> 45779
A2: Time
A3: Row Labels | B3: Sum of Likes (Reactions) | C3: Sum of Shares | D3: Sum of Comments | E3: Sum of Impressions | F3: Sum of Clicks | G3: Sum of Conversions | H3: Sum of Spend, GBP | I3: Sum of Total conversion value, GBP
A4: Birmingham | B4: 185369.4 | C4: 33005 | D4: 18682 | E4: 3971619.6 | F4: 44450.422 | G4: 12798 | H4: 39484.204 | I4: 550019.08
A5: London | B5: 210199.2 | C5: 43692.5 | D5: 30964 | E5: 5671356 | F5: 74284.831 | G5: 13080 | H5: 66704.461 | I5: 532011.48
A6: Manchester | B6: 212919 | C6: 42556.5 | D6: 21884.5 | E6: 5002473.2 | F6: 62850.769 | G6: 14374 | H6: 57061.402 | I6: 649669.88
A7: Grand Total | B7: 608487.6 | C7: 119254 | D7: 71530.5 | E7: 14645449 | F7: 181586.02 | G7: 40252 | H7: 163250.07 | I7: 1731700.4
A10: Location | B10: Likes | C10: Shares | D10: Comments | E10: Impressions | F10: Clicks | G10: Conversion | H10: Spend GBP
A11: =A4 -> Birmingham | B11: =B4 -> 185369.4 | C11: =C4 -> 33005 | D11: =D4 -> 18682 | E11: =E4 -> 3971619.6 | F11: =F4 -> 44450.422 | G11: =G4 -> 12798 | H11: =H4 -> 39484.204
A12: =A5 -> London | B12: =B5 -> 210199.2 | C12: =C5 -> 43692.5 | D12: =D5 -> 30964 | E12: =E5 -> 5671356 | F12: =F5 -> 74284.831 | G12: =G5 -> 13080 | H12: =H5 -> 66704.461
A13: =A6 -> Manchester | B13: =B6 -> 212919 | C13: =C6 -> 42556.5 | D13: =D6 -> 21884.5 | E13: =E6 -> 5002473.2 | F13: =F6 -> 62850.769 | G13: =G6 -> 14374 | H13: =H6 -> 57061.402
G14: Sum of Spend | H14: =GETPIVOTDATA("Sum of Spend, GBP",$A$3) -> 163250.07
G15: Sum of Conversion Rate (GBP) | H15: =GETPIVOTDATA("Sum of Total conversion value, GBP",$A$3) -> 1731700.4
A16: Location | B16: Impressions | D16: Location | E16: Clicks | G16: Location | H16: Conversion
A17: =A4 -> Birmingham | B17: =GETPIVOTDATA("Sum of Impressions",$A$3,"City/Location","Birmingham") -> 3971619.6 | D17: =A4 -> Birmingham | E17: =GETPIVOTDATA("Sum of Clicks",$A$3,"City/Location","Birmingham") -> 44450.422 | G17: =A4 -> Birmingham | H17: =GETPIVOTDATA("Sum of Conversions",$A$3,"City/Location","Birmingham") -> 12798
A18: =A5 -> London | B18: =GETPIVOTDATA("Sum of Impressions",$A$3,"City/Location","London") -> 5671356 | D18: =A5 -> London | E18: =GETPIVOTDATA("Sum of Clicks",$A$3,"City/Location","London") -> 74284.831 | G18: =A5 -> London | H18: =GETPIVOTDATA("Sum of Conversions",$A$3,"City/Location","London") -> 13080
A19: =A6 -> Manchester | B19: =GETPIVOTDATA("Sum of Impressions",$A$3,"City/Location","Manchester") -> 5002473.2 | D19: =A6 -> Manchester | E19: =GETPIVOTDATA("Sum of Clicks",$A$3,"City/Location","Manchester") -> 62850.769 | G19: =A6 -> Manchester | H19: =GETPIVOTDATA("Sum of Conversions",$A$3,"City/Location","Manchester") -> 14374
A23: Location | B23: Likes | D23: Location | E23: Shares | G23: Location | H23: Comments
A24: =A11 -> Birmingham | B24: =B4 -> 185369.4 | D24: =A11 -> Birmingham | E24: =GETPIVOTDATA("Sum of Shares",$A$3,"City/Location","Birmingham") -> 33005 | G24: =A11 -> Birmingham | H24: =GETPIVOTDATA("Sum of Comments",$A$3,"City/Location","Birmingham") -> 18682
A25: =A12 -> London | B25: =B5 -> 210199.2 | D25: =A12 -> London | E25: =GETPIVOTDATA("Sum of Shares",$A$3,"City/Location","London") -> 43692.5 | G25: =A12 -> London | H25: =GETPIVOTDATA("Sum of Comments",$A$3,"City/Location","London") -> 30964
A26: =A13 -> Manchester | B26: =B6 -> 212919 | D26: =A13 -> Manchester | E26: =GETPIVOTDATA("Sum of Shares",$A$3,"City/Location","Manchester") -> 42556.5 | G26: =A13 -> Manchester | H26: =GETPIVOTDATA("Sum of Comments",$A$3,"City/Location","Manchester") -> 21884.5
A27: Total Likes | B27: =GETPIVOTDATA("Sum of Likes (Reactions)",$A$3) -> 608487.6 | D27: Total Shares | E27: =GETPIVOTDATA("Sum of Shares",$A$3) -> 119254 | G27: Total Comments | H27: =GETPIVOTDATA("Sum of Comments",$A$3) -> 71530.5
A30: Location | B30: Spend GBP
A31: =A4 -> Birmingham | B31: =GETPIVOTDATA("Sum of Spend, GBP",$A$3,"City/Location","Birmingham") -> 39484.204
A32: =A5 -> London | B32: =GETPIVOTDATA("Sum of Spend, GBP",$A$3,"City/Location","London") -> 66704.461
A33: =A6 -> Manchester | B33: =GETPIVOTDATA("Sum of Spend, GBP",$A$3,"City/Location","Manchester") -> 57061.402
A34: =A7 -> Grand Total | B34: =GETPIVOTDATA("Sum of Spend, GBP",$A$3) -> 163250.07

Sheet My Dashboard
